lunar_test/__init__.py
lunar_test-0.0.5.dist-info/METADATA
lunar_test-0.0.5.dist-info/WHEEL
lunar_test-0.0.5.dist-info/top_level.txt
lunar_test-0.0.5.dist-info/RECORD
