Metadata-Version: 2.1
Name: lunar-test
Version: 0.0.5
Summary: lunar_test
Home-page: https://github.com/RimoChan/lunar-Ci
Author: RimoChan
Author-email: the@librian.net
License: UNKNOWN
Platform: UNKNOWN
Classifier: Programming Language :: Python :: 3
Classifier: Operating System :: OS Independent
Requires-Python: >=3.6
Requires-Dist: lunar-python (>=1.0.29)
